CDNDrive/__init__.py
CDNDrive/__main__.py
CDNDrive/util.py
CDNDrive/drivers/AliApi.py
CDNDrive/drivers/AutoHomeApi.py
CDNDrive/drivers/BaijiaApi.py
CDNDrive/drivers/BaseApi.py
CDNDrive/drivers/BiliApi.py
CDNDrive/drivers/CsdnApi.py
CDNDrive/drivers/JianApi.py
CDNDrive/drivers/NeteApi.py
CDNDrive/drivers/OscApi.py
CDNDrive/drivers/SogouApi.py
CDNDrive/drivers/SohuApi.py
CDNDrive/drivers/WeiboApi.py
CDNDrive/drivers/__init__.py
CDNDrive/encoders/GifEncoder.py
CDNDrive/encoders/JpgCatEncoder.py
CDNDrive/encoders/PngEncoder.py
CDNDrive/encoders/__init__.py
CDNDrive-2022.3.20.3.dist-info/LICENSE
CDNDrive-2022.3.20.3.dist-info/METADATA
CDNDrive-2022.3.20.3.dist-info/WHEEL
CDNDrive-2022.3.20.3.dist-info/entry_points.txt
CDNDrive-2022.3.20.3.dist-info/top_level.txt
CDNDrive-2022.3.20.3.dist-info/RECORD
