Metadata-Version: 2.1
Name: CDNDrive
Version: 2022.3.20.3
Summary: ☁️ CDNDrive，支持任意文件的全速上传与下载
Home-page: https://github.com/apachecn/CDNDrive
Author: ApacheCN
Author-email: apachecn@163.com
License: UNKNOWN
Keywords: cdn,cloud,picbed,disk,drive,storage,pan,yun,网盘,图床,云
Platform: UNKNOWN
Classifier: Development Status :: 4 - Beta
Classifier: Environment :: Console
Classifier: Intended Audience :: Developers
Classifier: Intended Audience :: End Users/Desktop
Classifier: License :: Other/Proprietary License
Classifier: Natural Language :: Chinese (Simplified)
Classifier: Natural Language :: English
Classifier: Operating System :: OS Independent
Classifier: Programming Language :: Python :: 3
Classifier: Programming Language :: Python :: 3 :: Only
Classifier: Programming Language :: Python :: 3.6
Classifier: Programming Language :: Python :: 3.7
Classifier: Topic :: Communications :: File Sharing
Classifier: Topic :: Internet :: WWW/HTTP
Classifier: Topic :: Utilities
Requires-Python: >=3.6
Requires-Dist: requests
Requires-Dist: rsa
Requires-Dist: pillow
Requires-Dist: numpy
